lektor_make/__init__.py
lektor_make/py.typed
lektor_make-0.3.dist-info/LICENSE
lektor_make-0.3.dist-info/METADATA
lektor_make-0.3.dist-info/WHEEL
lektor_make-0.3.dist-info/entry_points.txt
lektor_make-0.3.dist-info/top_level.txt
lektor_make-0.3.dist-info/RECORD
